{
	"BodyType": 1,
	"Bone": {
		"ForeHeadTY": 19,
		"ForeHeadTZ": -53,
		"AppleTX": -77,
		"AppleTY": 9,
		"AppleTZ": 16,
		"ChinTY": 68,
		"ChinTZ": 12,
		"MalarTX": 23,
		"MalarTY": -23,
		"MalarTZ": -57,
		"CheekTX": -20,
		"CheekTY": 0,
		"CheekTZ": 0,
		"ChinEdgeTX": -11,
		"ChinEdgeTY": 36,
		"ChinEdgeTZ": 13,
		"ChinBottomTX": 0,
		"ChinBottomTY": 0,
		"ChinBottomTZ": 0,
		"ForeHeadRX": -100,
		"AppleRY": 0,
		"AppleRZ": 0,
		"AppleRX": 0,
		"ChinRX": -30,
		"MalarRY": 22,
		"MalarRZ": 0,
		"MalarRX": 0,
		"CheekRY": 0,
		"CheekRZ": 0,
		"CheekRX": 0,
		"ChinBottomRX": 0,
		"ChinSX": -120,
		"ChinSY": 0,
		"ChinSZ": 1,
		"MalarSX": 0,
		"MalarSY": 0,
		"MalarSZ": 0,
		"CheekSX": 0,
		"CheekSY": 0,
		"CheekSZ": 0,
		"ChinEdgeSX": -78,
		"ChinEdgeSY": 0,
		"ChinEdgeSZ": 0,
		"ChinBottomSX": -22,
		"ChinBottomSZ": -4,
		"UMouthGrpTZ": 55,
		"UMouthGrpSY": 24
	}
}