{
	"BodyType": 2,
	"Bone": {
		"EyeGrpTX": 20,
		"EyeGrpTY": -71,
		"EyeGrpTZ": -53,
		"EyeUTX": 22,
		"EyeUTZ": -10,
		"EyeDTX": 13,
		"EyeDTZ": -20,
		"EyeITX": -14,
		"EyeITZ": -10,
		"EyeOTX": 13,
		"EyeOTZ": -20,
		"EyeGrpRY": -8,
		"EyeGrpRZ": 5,
		"EyeGrpRX": 1,
		"EyeURY": 0,
		"EyeURX": 0,
		"EyeDRY": 0,
		"EyeDRZ": 0,
		"EyeIRY": 0,
		"EyeIRZ": 0,
		"EyeIRX": 0,
		"EyeORY": 0,
		"EyeORX": 0,
		"EyeGrpSX": 80,
		"EyeGrpSY": 0,
		"EyeGrpSZ": 7,
		"EyeUSX": 0,
		"EyeUSY": 0,
		"EyeUSZ": 0,
		"EyeDSY": 0,
		"EyeISY": 0,
		"EyeOSY": 0,
		"EyeLashURZ": -42,
		"EyeLashURX": 41,
		"EyeLashURY": -99,
		"EyeLashDRZ": -35,
		"EyeLashDRX": 0,
		"EyeLashDRY": 0,
		"EyeBallRZ": 3,
		"EyeBallRX": -4
	}
}